ms_thermo/__init__.py
ms_thermo/cli.py
ms_thermo/constants.py
ms_thermo/flame_params.py
ms_thermo/gasout.py
ms_thermo/kero_prim2cons.py
ms_thermo/mixture_state.py
ms_thermo/species.py
ms_thermo/state.py
ms_thermo/tadia.py
ms_thermo/yk_from_phi.py
ms_thermo/INPUT/2S_KERO_BFER.h5
ms_thermo/INPUT/Luche1.cti
ms_thermo/INPUT/__init__.py
ms_thermo/INPUT/default_gasout_input.yml
ms_thermo/INPUT/species_database.dat
ms_thermo/INPUT/__pycache__/__init__.cpython-311.pyc
ms_thermo/__pycache__/__init__.cpython-311.pyc
ms_thermo/__pycache__/cli.cpython-311.pyc
ms_thermo/__pycache__/constants.cpython-311.pyc
ms_thermo/__pycache__/flame_params.cpython-311.pyc
ms_thermo/__pycache__/gasout.cpython-311.pyc
ms_thermo/__pycache__/kero_prim2cons.cpython-311.pyc
ms_thermo/__pycache__/mixture_state.cpython-311.pyc
ms_thermo/__pycache__/species.cpython-311.pyc
ms_thermo/__pycache__/state.cpython-311.pyc
ms_thermo/__pycache__/tadia.cpython-311.pyc
ms_thermo/__pycache__/yk_from_phi.cpython-311.pyc
ms_thermo-1.1.0.dist-info/licenses/LICENSE
ms_thermo-1.1.0.dist-info/METADATA
ms_thermo-1.1.0.dist-info/WHEEL
ms_thermo-1.1.0.dist-info/entry_points.txt
ms_thermo-1.1.0.dist-info/top_level.txt
ms_thermo-1.1.0.dist-info/RECORD
