Metadata-Version: 2.4
Name: ms_thermo
Version: 1.1.0
Summary: Utilities to work on 2D and 3D structured grids
Author-email: CoopTeam-CERFACS <coop@cerfacs.fr>
License: CeCILL-B License
Project-URL: Homepage, https://gitlab.com/cerfacs/ms_thermo
Project-URL: Documentation, https://ms-thermo.readthedocs.io/en/latest/
Project-URL: Issues, https://gitlab.com/cerfacs/ms_thermo/-/issues
Project-URL: Changelog, https://gitlab.com/cerfacs/ms_thermo/-/blob/master/CHANGELOG.md
Keywords: MS THERMO API
Classifier: Programming Language :: Python :: 3.11
Classifier: Programming Language :: Python :: 3.12
Classifier: Programming Language :: Python :: 3.13
Requires-Python: >=3.11
License-File: LICENSE
Requires-Dist: numpy>=2.0
Requires-Dist: scipy
Requires-Dist: h5py
Requires-Dist: PyYAML
Requires-Dist: click
Requires-Dist: h5cross
Provides-Extra: docs
Requires-Dist: myst-parser; extra == "docs"
Requires-Dist: sphinx_rtd_theme; extra == "docs"
Requires-Dist: recommonmark; extra == "docs"
Provides-Extra: tests
Requires-Dist: pytest; extra == "tests"
Requires-Dist: pytest-coverage; extra == "tests"
Requires-Dist: pytest-allclose; extra == "tests"
Dynamic: license-file
